{"links": {"self": {"href": "data/repositories/osrf/srcsim/issues/142/comments/37127515.json"}, "html": {"href": "#!/osrf/srcsim/issues/142#comment-37127515"}}, "issue": {"links": {"self": {"href": "data/repositories/osrf/srcsim/issues/142.json"}}, "type": "issue", "id": 142, "repository": {"links": {"self": {"href": "data/repositories/osrf/srcsim.json"}, "html": {"href": "#!/osrf/srcsim"}, "avatar": {"href": "data/bytebucket.org/ravatar/{c41021d9-0217-4628-999d-7f8d82f98dcb}ts=c_plus_plus"}}, "type": "repository", "name": "srcsim", "full_name": "osrf/srcsim", "uuid": "{c41021d9-0217-4628-999d-7f8d82f98dcb}"}, "title": "localization and teleportation"}, "content": {"raw": "> it really does not matter where it is just so long as it is consistent\n\nI think you solved the mystery! :tada: The controller probably never knows that it has been translated, but as long as you give it offsets with respect to its current position, it will work.\n\n> My worry is that these lookups are going to fail during the competition and the world frame is not going to be available\n\nTogether with @iche033 we launched a constellation on CloudSim and checked that the world frame is available from the field computer:\n\n~~~\nroot@ip-172-31-23-39:/home/docker/ws#  rosrun tf tf_echo world pelvis\nAt time 59.388\n- Translation: [0.079, 0.023, 0.993]\n- Rotation: in Quaternion [-0.000, -0.000, -0.000, 1.000]\n            in RPY (radian) [-0.000, -0.000, -0.000]\n            in RPY (degree) [-0.000, -0.017, -0.004]\n~~~\n\nWe also teleported the robot:\n\n~~~\nroot@ip-172-31-23-39:/home/docker/ws# rosservice call /srcsim/finals/start_task 2 1\nsuccess: True\n~~~\n\nAnd checked that the orientation is updated on TF:\n\n~~~\nroot@ip-172-31-23-39:/home/docker/ws# rosrun tf tf_echo world pelvis\nAt time 68.356\n- Translation: [0.037, 0.067, 0.989]\n- Rotation: in Quaternion [-0.000, -0.000, -0.381, 0.925]\n            in RPY (radian) [-0.000, -0.000, -0.781]\n            in RPY (degree) [-0.000, -0.016, -44.758]\n~~~\n\nWe still need to check whether walking works, but no worries, the TF lookups using world frame are available.", "markup": "markdown", "html": "<blockquote>\n<p>it really does not matter where it is just so long as it is consistent</p>\n</blockquote>\n<p>I think you solved the mystery! <img class=\"emoji\" src=\"data/pf-emoji-service--cdn.us-east-1.prod.public.atl-paas.net/standard/551c9814-1d37-4573-819d-afab3afeaf32/48x48/1f389.png\" alt=\"\ud83c\udf89\" title=\":tada:\" data-emoji-short-name=\":tada:\" /> The controller probably never knows that it has been translated, but as long as you give it offsets with respect to its current position, it will work.</p>\n<blockquote>\n<p>My worry is that these lookups are going to fail during the competition and the world frame is not going to be available</p>\n</blockquote>\n<p>Together with @iche033 we launched a constellation on CloudSim and checked that the world frame is available from the field computer:</p>\n<div class=\"codehilite\"><pre><span></span>root@ip-172-31-23-39:/home/docker/ws#  rosrun tf tf_echo world pelvis\nAt time 59.388\n- Translation: [0.079, 0.023, 0.993]\n- Rotation: in Quaternion [-0.000, -0.000, -0.000, 1.000]\n            in RPY (radian) [-0.000, -0.000, -0.000]\n            in RPY (degree) [-0.000, -0.017, -0.004]\n</pre></div>\n\n\n<p>We also teleported the robot:</p>\n<div class=\"codehilite\"><pre><span></span>root@ip-172-31-23-39:/home/docker/ws# rosservice call /srcsim/finals/start_task 2 1\nsuccess: True\n</pre></div>\n\n\n<p>And checked that the orientation is updated on TF:</p>\n<div class=\"codehilite\"><pre><span></span>root@ip-172-31-23-39:/home/docker/ws# rosrun tf tf_echo world pelvis\nAt time 68.356\n- Translation: [0.037, 0.067, 0.989]\n- Rotation: in Quaternion [-0.000, -0.000, -0.381, 0.925]\n            in RPY (radian) [-0.000, -0.000, -0.781]\n            in RPY (degree) [-0.000, -0.016, -44.758]\n</pre></div>\n\n\n<p>We still need to check whether walking works, but no worries, the TF lookups using world frame are available.</p>", "type": "rendered"}, "created_on": "2017-05-25T00:10:54.310943+00:00", "user": {"display_name": "Louise Poubel", "uuid": "{5cfa2075-477b-4ded-bdb9-8d2479544ec4}", "links": {"self": {"href": "https://api.bitbucket.org/2.0/users/%7B5cfa2075-477b-4ded-bdb9-8d2479544ec4%7D"}, "html": {"href": "https://bitbucket.org/%7B5cfa2075-477b-4ded-bdb9-8d2479544ec4%7D/"}, "avatar": {"href": "https://avatar-management--avatars.us-west-2.prod.public.atl-paas.net/557058:6ff86fcb-b7ab-44a5-b8a6-f6d9cae8b6e8/7d903d90-c5ea-4182-b7ef-0d467e9e1c74/128"}}, "nickname": "chapulina", "type": "user", "account_id": "557058:6ff86fcb-b7ab-44a5-b8a6-f6d9cae8b6e8"}, "updated_on": null, "type": "issue_comment", "id": 37127515}