{"pagelen": 50, "values": [{"update": {"description": "* Hand-picked masses and inertias\r\n\r\n![satellite.png](https://bitbucket.org/repo/xEbAAe/images/2674257339-satellite.png)\r\n\r\n* Simple shapes (sphere and cylinder) for collisions around the wheel handles to improve contact\r\n\r\n![sat_handle.png](https://bitbucket.org/repo/xEbAAe/images/3905001825-sat_handle.png)\r\n\r\n* Joint friction (resistance effort) calculated to resist approximately 5 pounds of effort considering that the wheel has about 0.1 m radius:\r\n\r\n\r\n```\r\n5 pounds ~= 2.5 kg\r\n2.5 kg * 9.8 m/s^2 ~= 25 N\r\n25 N * 0.1 m = 2.5 Nm\r\n```", "title": "Satellite Dish", "destination": {"commit": {"hash": "d94042e8720d", "type": "commit", "links": {"self": {"href": "data/repositories/osrf/srcsim/commit/d94042e8720d.json"}, "html": {"href": "#!/osrf/srcsim/commits/d94042e8720d"}}}, "repository": {"links": {"self": {"href": "data/repositories/osrf/srcsim.json"}, "html": {"href": "#!/osrf/srcsim"}, "avatar": {"href": "data/bytebucket.org/ravatar/{c41021d9-0217-4628-999d-7f8d82f98dcb}ts=c_plus_plus"}}, "type": "repository", "name": "srcsim", "full_name": "osrf/srcsim", "uuid": "{c41021d9-0217-4628-999d-7f8d82f98dcb}"}, "branch": {"name": "default"}}, "reason": "", "source": {"commit": {"hash": "aa028f4a3607", "type": "commit", "links": {"self": {"href": "data/repositories/osrf/srcsim/commit/aa028f4a3607.json"}, "html": {"href": "#!/osrf/srcsim/commits/aa028f4a3607"}}}, "repository": {"links": {"self": {"href": "data/repositories/osrf/srcsim.json"}, "html": {"href": "#!/osrf/srcsim"}, "avatar": {"href": "data/bytebucket.org/ravatar/{c41021d9-0217-4628-999d-7f8d82f98dcb}ts=c_plus_plus"}}, "type": "repository", "name": "srcsim", "full_name": "osrf/srcsim", "uuid": "{c41021d9-0217-4628-999d-7f8d82f98dcb}"}, "branch": {"name": "satellite_dish"}}, "state": "MERGED", "author": {"display_name": "Louise Poubel", "uuid": "{5cfa2075-477b-4ded-bdb9-8d2479544ec4}", "links": {"self": {"href": "https://api.bitbucket.org/2.0/users/%7B5cfa2075-477b-4ded-bdb9-8d2479544ec4%7D"}, "html": {"href": "https://bitbucket.org/%7B5cfa2075-477b-4ded-bdb9-8d2479544ec4%7D/"}, "avatar": {"href": "https://avatar-management--avatars.us-west-2.prod.public.atl-paas.net/557058:6ff86fcb-b7ab-44a5-b8a6-f6d9cae8b6e8/7d903d90-c5ea-4182-b7ef-0d467e9e1c74/128"}}, "nickname": "chapulina", "type": "user", "account_id": "557058:6ff86fcb-b7ab-44a5-b8a6-f6d9cae8b6e8"}, "date": "2017-02-08T00:34:24.935853+00:00"}, "pull_request": {"type": "pullrequest", "id": 25, "links": {"self": {"href": "data/repositories/osrf/srcsim/pullrequests/25.json"}, "html": {"href": "#!/osrf/srcsim/pull-requests/25"}}, "title": "Satellite Dish"}}, {"approval": {"date": "2017-02-08T00:08:29.486458+00:00", "pullrequest": {"type": "pullrequest", "id": 25, "links": {"self": {"href": "data/repositories/osrf/srcsim/pullrequests/25.json"}, "html": {"href": "#!/osrf/srcsim/pull-requests/25"}}, "title": "Satellite Dish"}, "user": {"display_name": "Steve Peters", "uuid": "{2ccfed09-18b8-4921-8d58-15ef01092802}", "links": {"self": {"href": "https://api.bitbucket.org/2.0/users/%7B2ccfed09-18b8-4921-8d58-15ef01092802%7D"}, "html": {"href": "https://bitbucket.org/%7B2ccfed09-18b8-4921-8d58-15ef01092802%7D/"}, "avatar": {"href": "data/secure.gravatar.com/avatar/1fb4816dad9e68337d3096f750951f6cd=httpsavatar-management--avatars.us-west-2.prod.public.atl-paas.netinitialsSP-1.png"}}, "nickname": "Steven Peters", "type": "user", "account_id": "557058:5de38267-b118-494c-aa76-4fab35448816"}}, "pull_request": {"type": "pullrequest", "id": 25, "links": {"self": {"href": "data/repositories/osrf/srcsim/pullrequests/25.json"}, "html": {"href": "#!/osrf/srcsim/pull-requests/25"}}, "title": "Satellite Dish"}}, {"comment": {"links": {"self": {"href": "data/repositories/osrf/srcsim/pullrequests/25/comments/31068842.json"}, "html": {"href": "#!/osrf/srcsim/pull-requests/25/_/diff#comment-31068842"}}, "parent": {"id": 31067725, "links": {"self": {"href": "data/repositories/osrf/srcsim/pullrequests/25/comments/31067725.json"}, "html": {"href": "#!/osrf/srcsim/pull-requests/25/_/diff#comment-31067725"}}}, "deleted": false, "pullrequest": {"type": "pullrequest", "id": 25, "links": {"self": {"href": "data/repositories/osrf/srcsim/pullrequests/25.json"}, "html": {"href": "#!/osrf/srcsim/pull-requests/25"}}, "title": "Satellite Dish"}, "content": {"raw": "I would just try to make sure the feet of the tripod aren't contacting any static objects when the fixed joint is used", "markup": "markdown", "html": "<p>I would just try to make sure the feet of the tripod aren't contacting any static objects when the fixed joint is used</p>", "type": "rendered"}, "created_on": "2017-02-08T00:08:25.399630+00:00", "user": {"display_name": "Steve Peters", "uuid": "{2ccfed09-18b8-4921-8d58-15ef01092802}", "links": {"self": {"href": "https://api.bitbucket.org/2.0/users/%7B2ccfed09-18b8-4921-8d58-15ef01092802%7D"}, "html": {"href": "https://bitbucket.org/%7B2ccfed09-18b8-4921-8d58-15ef01092802%7D/"}, "avatar": {"href": "data/secure.gravatar.com/avatar/1fb4816dad9e68337d3096f750951f6cd=httpsavatar-management--avatars.us-west-2.prod.public.atl-paas.netinitialsSP-1.png"}}, "nickname": "Steven Peters", "type": "user", "account_id": "557058:5de38267-b118-494c-aa76-4fab35448816"}, "updated_on": "2017-02-08T00:08:25.402661+00:00", "type": "pullrequest_comment", "id": 31068842}, "pull_request": {"type": "pullrequest", "id": 25, "links": {"self": {"href": "data/repositories/osrf/srcsim/pullrequests/25.json"}, "html": {"href": "#!/osrf/srcsim/pull-requests/25"}}, "title": "Satellite Dish"}}, {"comment": {"links": {"self": {"href": "data/repositories/osrf/srcsim/pullrequests/25/comments/31067725.json"}, "html": {"href": "#!/osrf/srcsim/pull-requests/25/_/diff#comment-31067725"}}, "parent": {"id": 31066944, "links": {"self": {"href": "data/repositories/osrf/srcsim/pullrequests/25/comments/31066944.json"}, "html": {"href": "#!/osrf/srcsim/pull-requests/25/_/diff#comment-31066944"}}}, "deleted": false, "pullrequest": {"type": "pullrequest", "id": 25, "links": {"self": {"href": "data/repositories/osrf/srcsim/pullrequests/25.json"}, "html": {"href": "#!/osrf/srcsim/pull-requests/25"}}, "title": "Satellite Dish"}, "content": {"raw": "oh, that should be fine", "markup": "markdown", "html": "<p>oh, that should be fine</p>", "type": "rendered"}, "created_on": "2017-02-07T23:36:00.550292+00:00", "user": {"display_name": "Steve Peters", "uuid": "{2ccfed09-18b8-4921-8d58-15ef01092802}", "links": {"self": {"href": "https://api.bitbucket.org/2.0/users/%7B2ccfed09-18b8-4921-8d58-15ef01092802%7D"}, "html": {"href": "https://bitbucket.org/%7B2ccfed09-18b8-4921-8d58-15ef01092802%7D/"}, "avatar": {"href": "data/secure.gravatar.com/avatar/1fb4816dad9e68337d3096f750951f6cd=httpsavatar-management--avatars.us-west-2.prod.public.atl-paas.netinitialsSP-1.png"}}, "nickname": "Steven Peters", "type": "user", "account_id": "557058:5de38267-b118-494c-aa76-4fab35448816"}, "updated_on": "2017-02-07T23:36:00.553460+00:00", "type": "pullrequest_comment", "id": 31067725}, "pull_request": {"type": "pullrequest", "id": 25, "links": {"self": {"href": "data/repositories/osrf/srcsim/pullrequests/25.json"}, "html": {"href": "#!/osrf/srcsim/pull-requests/25"}}, "title": "Satellite Dish"}}, {"comment": {"links": {"self": {"href": "data/repositories/osrf/srcsim/pullrequests/25/comments/31066944.json"}, "html": {"href": "#!/osrf/srcsim/pull-requests/25/_/diff#comment-31066944"}}, "parent": {"id": 31065100, "links": {"self": {"href": "data/repositories/osrf/srcsim/pullrequests/25/comments/31065100.json"}, "html": {"href": "#!/osrf/srcsim/pull-requests/25/_/diff#comment-31065100"}}}, "deleted": false, "pullrequest": {"type": "pullrequest", "id": 25, "links": {"self": {"href": "data/repositories/osrf/srcsim/pullrequests/25.json"}, "html": {"href": "#!/osrf/srcsim/pull-requests/25"}}, "title": "Satellite Dish"}, "content": {"raw": "Sure. But in any case I was going to attach it to the world with a fixed joint. Do you think that's stable enough?", "markup": "markdown", "html": "<p>Sure. But in any case I was going to attach it to the world with a fixed joint. Do you think that's stable enough?</p>", "type": "rendered"}, "created_on": "2017-02-07T23:17:45.530844+00:00", "user": {"display_name": "Louise Poubel", "uuid": "{5cfa2075-477b-4ded-bdb9-8d2479544ec4}", "links": {"self": {"href": "https://api.bitbucket.org/2.0/users/%7B5cfa2075-477b-4ded-bdb9-8d2479544ec4%7D"}, "html": {"href": "https://bitbucket.org/%7B5cfa2075-477b-4ded-bdb9-8d2479544ec4%7D/"}, "avatar": {"href": "https://avatar-management--avatars.us-west-2.prod.public.atl-paas.net/557058:6ff86fcb-b7ab-44a5-b8a6-f6d9cae8b6e8/7d903d90-c5ea-4182-b7ef-0d467e9e1c74/128"}}, "nickname": "chapulina", "type": "user", "account_id": "557058:6ff86fcb-b7ab-44a5-b8a6-f6d9cae8b6e8"}, "updated_on": "2017-02-07T23:17:45.533171+00:00", "type": "pullrequest_comment", "id": 31066944}, "pull_request": {"type": "pullrequest", "id": 25, "links": {"self": {"href": "data/repositories/osrf/srcsim/pullrequests/25.json"}, "html": {"href": "#!/osrf/srcsim/pull-requests/25"}}, "title": "Satellite Dish"}}, {"comment": {"links": {"self": {"href": "data/repositories/osrf/srcsim/pullrequests/25/comments/31066245.json"}, "html": {"href": "#!/osrf/srcsim/pull-requests/25/_/diff#comment-31066245"}}, "parent": {"id": 31065014, "links": {"self": {"href": "data/repositories/osrf/srcsim/pullrequests/25/comments/31065014.json"}, "html": {"href": "#!/osrf/srcsim/pull-requests/25/_/diff#comment-31065014"}}}, "deleted": false, "pullrequest": {"type": "pullrequest", "id": 25, "links": {"self": {"href": "data/repositories/osrf/srcsim/pullrequests/25.json"}, "html": {"href": "#!/osrf/srcsim/pull-requests/25"}}, "title": "Satellite Dish"}, "content": {"raw": "Changed: aa028f4", "markup": "markdown", "html": "<p>Changed: <a href=\"#!/osrf/srcsim/commits/aa028f4\" rel=\"nofollow\" class=\"ap-connect-link\">aa028f4</a></p>", "type": "rendered"}, "created_on": "2017-02-07T23:03:09.558438+00:00", "user": {"display_name": "Louise Poubel", "uuid": "{5cfa2075-477b-4ded-bdb9-8d2479544ec4}", "links": {"self": {"href": "https://api.bitbucket.org/2.0/users/%7B5cfa2075-477b-4ded-bdb9-8d2479544ec4%7D"}, "html": {"href": "https://bitbucket.org/%7B5cfa2075-477b-4ded-bdb9-8d2479544ec4%7D/"}, "avatar": {"href": "https://avatar-management--avatars.us-west-2.prod.public.atl-paas.net/557058:6ff86fcb-b7ab-44a5-b8a6-f6d9cae8b6e8/7d903d90-c5ea-4182-b7ef-0d467e9e1c74/128"}}, "nickname": "chapulina", "type": "user", "account_id": "557058:6ff86fcb-b7ab-44a5-b8a6-f6d9cae8b6e8"}, "inline": {}, "updated_on": "2017-02-07T23:03:09.561765+00:00", "type": "pullrequest_comment", "id": 31066245}, "pull_request": {"type": "pullrequest", "id": 25, "links": {"self": {"href": "data/repositories/osrf/srcsim/pullrequests/25.json"}, "html": {"href": "#!/osrf/srcsim/pull-requests/25"}}, "title": "Satellite Dish"}}, {"update": {"description": "* Hand-picked masses and inertias\r\n\r\n![satellite.png](https://bitbucket.org/repo/xEbAAe/images/2674257339-satellite.png)\r\n\r\n* Simple shapes (sphere and cylinder) for collisions around the wheel handles to improve contact\r\n\r\n![sat_handle.png](https://bitbucket.org/repo/xEbAAe/images/3905001825-sat_handle.png)\r\n\r\n* Joint friction (resistance effort) calculated to resist approximately 5 pounds of effort considering that the wheel has about 0.1 m radius:\r\n\r\n\r\n```\r\n5 pounds ~= 2.5 kg\r\n2.5 kg * 9.8 m/s^2 ~= 25 N\r\n25 N * 0.1 m = 2.5 Nm\r\n```", "title": "Satellite Dish", "destination": {"commit": {"hash": "ace23db5c5fc", "type": "commit", "links": {"self": {"href": "data/repositories/osrf/srcsim/commit/ace23db5c5fc.json"}, "html": {"href": "#!/osrf/srcsim/commits/ace23db5c5fc"}}}, "repository": {"links": {"self": {"href": "data/repositories/osrf/srcsim.json"}, "html": {"href": "#!/osrf/srcsim"}, "avatar": {"href": "data/bytebucket.org/ravatar/{c41021d9-0217-4628-999d-7f8d82f98dcb}ts=c_plus_plus"}}, "type": "repository", "name": "srcsim", "full_name": "osrf/srcsim", "uuid": "{c41021d9-0217-4628-999d-7f8d82f98dcb}"}, "branch": {"name": "default"}}, "reason": "", "source": {"commit": {"hash": "aa028f4a3607", "type": "commit", "links": {"self": {"href": "data/repositories/osrf/srcsim/commit/aa028f4a3607.json"}, "html": {"href": "#!/osrf/srcsim/commits/aa028f4a3607"}}}, "repository": {"links": {"self": {"href": "data/repositories/osrf/srcsim.json"}, "html": {"href": "#!/osrf/srcsim"}, "avatar": {"href": "data/bytebucket.org/ravatar/{c41021d9-0217-4628-999d-7f8d82f98dcb}ts=c_plus_plus"}}, "type": "repository", "name": "srcsim", "full_name": "osrf/srcsim", "uuid": "{c41021d9-0217-4628-999d-7f8d82f98dcb}"}, "branch": {"name": "satellite_dish"}}, "state": "OPEN", "author": {"display_name": "Louise Poubel", "uuid": "{5cfa2075-477b-4ded-bdb9-8d2479544ec4}", "links": {"self": {"href": "https://api.bitbucket.org/2.0/users/%7B5cfa2075-477b-4ded-bdb9-8d2479544ec4%7D"}, "html": {"href": "https://bitbucket.org/%7B5cfa2075-477b-4ded-bdb9-8d2479544ec4%7D/"}, "avatar": {"href": "https://avatar-management--avatars.us-west-2.prod.public.atl-paas.net/557058:6ff86fcb-b7ab-44a5-b8a6-f6d9cae8b6e8/7d903d90-c5ea-4182-b7ef-0d467e9e1c74/128"}}, "nickname": "chapulina", "type": "user", "account_id": "557058:6ff86fcb-b7ab-44a5-b8a6-f6d9cae8b6e8"}, "date": "2017-02-07T23:02:50.615665+00:00"}, "pull_request": {"type": "pullrequest", "id": 25, "links": {"self": {"href": "data/repositories/osrf/srcsim/pullrequests/25.json"}, "html": {"href": "#!/osrf/srcsim/pull-requests/25"}}, "title": "Satellite Dish"}}, {"comment": {"links": {"self": {"href": "data/repositories/osrf/srcsim/pullrequests/25/comments/31065100.json"}, "html": {"href": "#!/osrf/srcsim/pull-requests/25/_/diff#comment-31065100"}}, "deleted": false, "pullrequest": {"type": "pullrequest", "id": 25, "links": {"self": {"href": "data/repositories/osrf/srcsim/pullrequests/25.json"}, "html": {"href": "#!/osrf/srcsim/pull-requests/25"}}, "title": "Satellite Dish"}, "content": {"raw": "the feet of the satellite dish are a little concerning, as the contacts look a bit unstable. Perhaps we could add some spheres are the tripod corners with good contact parameters?", "markup": "markdown", "html": "<p>the feet of the satellite dish are a little concerning, as the contacts look a bit unstable. Perhaps we could add some spheres are the tripod corners with good contact parameters?</p>", "type": "rendered"}, "created_on": "2017-02-07T22:39:54.004200+00:00", "user": {"display_name": "Steve Peters", "uuid": "{2ccfed09-18b8-4921-8d58-15ef01092802}", "links": {"self": {"href": "https://api.bitbucket.org/2.0/users/%7B2ccfed09-18b8-4921-8d58-15ef01092802%7D"}, "html": {"href": "https://bitbucket.org/%7B2ccfed09-18b8-4921-8d58-15ef01092802%7D/"}, "avatar": {"href": "data/secure.gravatar.com/avatar/1fb4816dad9e68337d3096f750951f6cd=httpsavatar-management--avatars.us-west-2.prod.public.atl-paas.netinitialsSP-1.png"}}, "nickname": "Steven Peters", "type": "user", "account_id": "557058:5de38267-b118-494c-aa76-4fab35448816"}, "updated_on": "2017-02-07T22:39:54.007222+00:00", "type": "pullrequest_comment", "id": 31065100}, "pull_request": {"type": "pullrequest", "id": 25, "links": {"self": {"href": "data/repositories/osrf/srcsim/pullrequests/25.json"}, "html": {"href": "#!/osrf/srcsim/pull-requests/25"}}, "title": "Satellite Dish"}}, {"comment": {"links": {"self": {"href": "data/repositories/osrf/srcsim/pullrequests/25/comments/31065014.json"}, "html": {"href": "#!/osrf/srcsim/pull-requests/25/_/diff#comment-31065014"}}, "parent": {"id": 31064775, "links": {"self": {"href": "data/repositories/osrf/srcsim/pullrequests/25/comments/31064775.json"}, "html": {"href": "#!/osrf/srcsim/pull-requests/25/_/diff#comment-31064775"}}}, "deleted": false, "pullrequest": {"type": "pullrequest", "id": 25, "links": {"self": {"href": "data/repositories/osrf/srcsim/pullrequests/25.json"}, "html": {"href": "#!/osrf/srcsim/pull-requests/25"}}, "title": "Satellite Dish"}, "content": {"raw": "this should be smaller by a factor of 10", "markup": "markdown", "html": "<p>this should be smaller by a factor of 10</p>", "type": "rendered"}, "created_on": "2017-02-07T22:38:22.193594+00:00", "user": {"display_name": "Steve Peters", "uuid": "{2ccfed09-18b8-4921-8d58-15ef01092802}", "links": {"self": {"href": "https://api.bitbucket.org/2.0/users/%7B2ccfed09-18b8-4921-8d58-15ef01092802%7D"}, "html": {"href": "https://bitbucket.org/%7B2ccfed09-18b8-4921-8d58-15ef01092802%7D/"}, "avatar": {"href": "data/secure.gravatar.com/avatar/1fb4816dad9e68337d3096f750951f6cd=httpsavatar-management--avatars.us-west-2.prod.public.atl-paas.netinitialsSP-1.png"}}, "nickname": "Steven Peters", "type": "user", "account_id": "557058:5de38267-b118-494c-aa76-4fab35448816"}, "inline": {}, "updated_on": "2017-02-07T22:38:22.197552+00:00", "type": "pullrequest_comment", "id": 31065014}, "pull_request": {"type": "pullrequest", "id": 25, "links": {"self": {"href": "data/repositories/osrf/srcsim/pullrequests/25.json"}, "html": {"href": "#!/osrf/srcsim/pull-requests/25"}}, "title": "Satellite Dish"}}, {"comment": {"links": {"self": {"href": "data/repositories/osrf/srcsim/pullrequests/25/comments/31064775.json"}, "html": {"href": "#!/osrf/srcsim/pull-requests/25/_/diff#comment-31064775"}}, "deleted": false, "pullrequest": {"type": "pullrequest", "id": 25, "links": {"self": {"href": "data/repositories/osrf/srcsim/pullrequests/25.json"}, "html": {"href": "#!/osrf/srcsim/pull-requests/25"}}, "title": "Satellite Dish"}, "content": {"raw": "This mass seems a bit too big too", "markup": "markdown", "html": "<p>This mass seems a bit too big too</p>", "type": "rendered"}, "created_on": "2017-02-07T22:34:23.428589+00:00", "user": {"display_name": "Steve Peters", "uuid": "{2ccfed09-18b8-4921-8d58-15ef01092802}", "links": {"self": {"href": "https://api.bitbucket.org/2.0/users/%7B2ccfed09-18b8-4921-8d58-15ef01092802%7D"}, "html": {"href": "https://bitbucket.org/%7B2ccfed09-18b8-4921-8d58-15ef01092802%7D/"}, "avatar": {"href": "data/secure.gravatar.com/avatar/1fb4816dad9e68337d3096f750951f6cd=httpsavatar-management--avatars.us-west-2.prod.public.atl-paas.netinitialsSP-1.png"}}, "nickname": "Steven Peters", "type": "user", "account_id": "557058:5de38267-b118-494c-aa76-4fab35448816"}, "inline": {}, "updated_on": "2017-02-07T22:34:23.431888+00:00", "type": "pullrequest_comment", "id": 31064775}, "pull_request": {"type": "pullrequest", "id": 25, "links": {"self": {"href": "data/repositories/osrf/srcsim/pullrequests/25.json"}, "html": {"href": "#!/osrf/srcsim/pull-requests/25"}}, "title": "Satellite Dish"}}, {"update": {"description": "* Hand-picked masses and inertias\r\n\r\n![satellite.png](https://bitbucket.org/repo/xEbAAe/images/2674257339-satellite.png)\r\n\r\n* Simple shapes (sphere and cylinder) for collisions around the wheel handles to improve contact\r\n\r\n![sat_handle.png](https://bitbucket.org/repo/xEbAAe/images/3905001825-sat_handle.png)\r\n\r\n* Joint friction (resistance effort) calculated to resist approximately 5 pounds of effort considering that the wheel has about 0.1 m radius:\r\n\r\n\r\n```\r\n5 pounds ~= 2.5 kg\r\n2.5 kg * 9.8 m/s^2 ~= 25 N\r\n25 N * 0.1 m = 2.5 Nm\r\n```", "title": "Satellite Dish", "destination": {"commit": {"hash": "ace23db5c5fc", "type": "commit", "links": {"self": {"href": "data/repositories/osrf/srcsim/commit/ace23db5c5fc.json"}, "html": {"href": "#!/osrf/srcsim/commits/ace23db5c5fc"}}}, "repository": {"links": {"self": {"href": "data/repositories/osrf/srcsim.json"}, "html": {"href": "#!/osrf/srcsim"}, "avatar": {"href": "data/bytebucket.org/ravatar/{c41021d9-0217-4628-999d-7f8d82f98dcb}ts=c_plus_plus"}}, "type": "repository", "name": "srcsim", "full_name": "osrf/srcsim", "uuid": "{c41021d9-0217-4628-999d-7f8d82f98dcb}"}, "branch": {"name": "default"}}, "reason": "", "source": {"commit": {"hash": "12870dbd6c25", "type": "commit", "links": {"self": {"href": "data/repositories/osrf/srcsim/commit/12870dbd6c25.json"}, "html": {"href": "#!/osrf/srcsim/commits/12870dbd6c25"}}}, "repository": {"links": {"self": {"href": "data/repositories/osrf/srcsim.json"}, "html": {"href": "#!/osrf/srcsim"}, "avatar": {"href": "data/bytebucket.org/ravatar/{c41021d9-0217-4628-999d-7f8d82f98dcb}ts=c_plus_plus"}}, "type": "repository", "name": "srcsim", "full_name": "osrf/srcsim", "uuid": "{c41021d9-0217-4628-999d-7f8d82f98dcb}"}, "branch": {"name": "satellite_dish"}}, "state": "OPEN", "author": {"display_name": "Louise Poubel", "uuid": "{5cfa2075-477b-4ded-bdb9-8d2479544ec4}", "links": {"self": {"href": "https://api.bitbucket.org/2.0/users/%7B5cfa2075-477b-4ded-bdb9-8d2479544ec4%7D"}, "html": {"href": "https://bitbucket.org/%7B5cfa2075-477b-4ded-bdb9-8d2479544ec4%7D/"}, "avatar": {"href": "https://avatar-management--avatars.us-west-2.prod.public.atl-paas.net/557058:6ff86fcb-b7ab-44a5-b8a6-f6d9cae8b6e8/7d903d90-c5ea-4182-b7ef-0d467e9e1c74/128"}}, "nickname": "chapulina", "type": "user", "account_id": "557058:6ff86fcb-b7ab-44a5-b8a6-f6d9cae8b6e8"}, "date": "2017-02-07T19:00:33.202555+00:00"}, "pull_request": {"type": "pullrequest", "id": 25, "links": {"self": {"href": "data/repositories/osrf/srcsim/pullrequests/25.json"}, "html": {"href": "#!/osrf/srcsim/pull-requests/25"}}, "title": "Satellite Dish"}}, {"update": {"description": "* Hand-picked masses and inertias\r\n\r\n![satellite.png](https://bitbucket.org/repo/xEbAAe/images/2674257339-satellite.png)\r\n\r\n* Simple shapes (sphere and cylinder) for collisions around the wheel handles to improve contact\r\n\r\n![sat_handle.png](https://bitbucket.org/repo/xEbAAe/images/3905001825-sat_handle.png)\r\n\r\n* Joint friction (resistance effort) calculated to resist approximately 5 pounds of effort considering that the wheel has about 0.1 m radius:\r\n\r\n\r\n```\r\n5 pounds ~= 2.5 kg\r\n2.5 kg * 9.8 m/s^2 ~= 25 N\r\n25 N * 0.1 m = 2.5 Nm\r\n```", "title": "Satellite Dish", "destination": {"commit": {"hash": "ace23db5c5fc", "type": "commit", "links": {"self": {"href": "data/repositories/osrf/srcsim/commit/ace23db5c5fc.json"}, "html": {"href": "#!/osrf/srcsim/commits/ace23db5c5fc"}}}, "repository": {"links": {"self": {"href": "data/repositories/osrf/srcsim.json"}, "html": {"href": "#!/osrf/srcsim"}, "avatar": {"href": "data/bytebucket.org/ravatar/{c41021d9-0217-4628-999d-7f8d82f98dcb}ts=c_plus_plus"}}, "type": "repository", "name": "srcsim", "full_name": "osrf/srcsim", "uuid": "{c41021d9-0217-4628-999d-7f8d82f98dcb}"}, "branch": {"name": "default"}}, "reason": "", "source": {"commit": {"hash": "12870dbd6c25", "type": "commit", "links": {"self": {"href": "data/repositories/osrf/srcsim/commit/12870dbd6c25.json"}, "html": {"href": "#!/osrf/srcsim/commits/12870dbd6c25"}}}, "repository": {"links": {"self": {"href": "data/repositories/osrf/srcsim.json"}, "html": {"href": "#!/osrf/srcsim"}, "avatar": {"href": "data/bytebucket.org/ravatar/{c41021d9-0217-4628-999d-7f8d82f98dcb}ts=c_plus_plus"}}, "type": "repository", "name": "srcsim", "full_name": "osrf/srcsim", "uuid": "{c41021d9-0217-4628-999d-7f8d82f98dcb}"}, "branch": {"name": "satellite_dish"}}, "state": "OPEN", "author": {"display_name": "Louise Poubel", "uuid": "{5cfa2075-477b-4ded-bdb9-8d2479544ec4}", "links": {"self": {"href": "https://api.bitbucket.org/2.0/users/%7B5cfa2075-477b-4ded-bdb9-8d2479544ec4%7D"}, "html": {"href": "https://bitbucket.org/%7B5cfa2075-477b-4ded-bdb9-8d2479544ec4%7D/"}, "avatar": {"href": "https://avatar-management--avatars.us-west-2.prod.public.atl-paas.net/557058:6ff86fcb-b7ab-44a5-b8a6-f6d9cae8b6e8/7d903d90-c5ea-4182-b7ef-0d467e9e1c74/128"}}, "nickname": "chapulina", "type": "user", "account_id": "557058:6ff86fcb-b7ab-44a5-b8a6-f6d9cae8b6e8"}, "date": "2017-02-07T19:00:33.179069+00:00"}, "pull_request": {"type": "pullrequest", "id": 25, "links": {"self": {"href": "data/repositories/osrf/srcsim/pullrequests/25.json"}, "html": {"href": "#!/osrf/srcsim/pull-requests/25"}}, "title": "Satellite Dish"}}]}