{"pagelen": 100, "values": [{"changes": {"content": {"new": "The controller manager crashes as it tries to initialize the hardware interface.  This continues after updating with the fix for the $HOME/valkyrie directory missing issue (issue #4).\r\n\r\nSee the log:\r\n\r\nx1:~$ roslaunch srcsim qual2.launch extra_gazebo_ar", "old": "The controller manager crashes as it tries to initialize the hardware interface.  This continues after updating with the fix for the $HOME/valkarie directory missing issue.\r\n\r\nSee the log:\r\n\r\nx1:~$ roslaunch srcsim qual2.launch extra_gazebo_args:=\"-r\" in"}}, "links": {"self": {"href": "data/repositories/osrf/srcsim/issues/6/changes/31945008.json"}, "html": {"href": "#!/osrf/srcsim/issues/6#comment-31945008"}}, "issue": {"links": {"self": {"href": "data/repositories/osrf/srcsim/issues/6.json"}}, "type": "issue", "id": 6, "repository": {"links": {"self": {"href": "data/repositories/osrf/srcsim.json"}, "html": {"href": "#!/osrf/srcsim"}, "avatar": {"href": "data/bytebucket.org/ravatar/{c41021d9-0217-4628-999d-7f8d82f98dcb}ts=c_plus_plus"}}, "type": "repository", "name": "srcsim", "full_name": "osrf/srcsim", "uuid": "{c41021d9-0217-4628-999d-7f8d82f98dcb}"}, "title": "controller manager dies"}, "created_on": "2016-11-07T01:49:57.093581+00:00", "user": {"display_name": "dan", "uuid": "{a93bd0ec-35fc-49a5-aa8a-b0b57403c2d0}", "links": {"self": {"href": "https://api.bitbucket.org/2.0/users/%7Ba93bd0ec-35fc-49a5-aa8a-b0b57403c2d0%7D"}, "html": {"href": "https://bitbucket.org/%7Ba93bd0ec-35fc-49a5-aa8a-b0b57403c2d0%7D/"}, "avatar": {"href": "data/secure.gravatar.com/avatar/dd56d3105d7602d83d5c35a320f6b36cd=httpsavatar-management--avatars.us-west-2.prod.public.atl-paas.netinitialsD-6.png"}}, "nickname": "dan77062", "type": "user", "account_id": "557058:e0e36946-cb60-4776-8f47-2e9a0285ad35"}, "message": {"raw": null, "markup": "markdown", "html": "", "type": "rendered"}, "type": "issue_change", "id": 31945008}, {"changes": {"content": {"new": "The controller manager crashes as it tries to initialize the hardware interface.  This continues after updating with the fix for the $HOME/valkyrie directory missing issue (issue #4).  See the log below.\r\n\r\nI am wondering if it is a race condition.  It w", "old": "The controller manager crashes as it tries to initialize the hardware interface.  This continues after updating with the fix for the $HOME/valkyrie directory missing issue (issue #4).\r\n\r\nSee the log:\r\n\r\nx1:~$ roslaunch srcsim qual2.launch extra_gazebo_ar"}}, "links": {"self": {"href": "data/repositories/osrf/srcsim/issues/6/changes/31945365.json"}, "html": {"href": "#!/osrf/srcsim/issues/6#comment-31945365"}}, "issue": {"links": {"self": {"href": "data/repositories/osrf/srcsim/issues/6.json"}}, "type": "issue", "id": 6, "repository": {"links": {"self": {"href": "data/repositories/osrf/srcsim.json"}, "html": {"href": "#!/osrf/srcsim"}, "avatar": {"href": "data/bytebucket.org/ravatar/{c41021d9-0217-4628-999d-7f8d82f98dcb}ts=c_plus_plus"}}, "type": "repository", "name": "srcsim", "full_name": "osrf/srcsim", "uuid": "{c41021d9-0217-4628-999d-7f8d82f98dcb}"}, "title": "controller manager dies"}, "created_on": "2016-11-07T02:34:43.506386+00:00", "user": {"display_name": "dan", "uuid": "{a93bd0ec-35fc-49a5-aa8a-b0b57403c2d0}", "links": {"self": {"href": "https://api.bitbucket.org/2.0/users/%7Ba93bd0ec-35fc-49a5-aa8a-b0b57403c2d0%7D"}, "html": {"href": "https://bitbucket.org/%7Ba93bd0ec-35fc-49a5-aa8a-b0b57403c2d0%7D/"}, "avatar": {"href": "data/secure.gravatar.com/avatar/dd56d3105d7602d83d5c35a320f6b36cd=httpsavatar-management--avatars.us-west-2.prod.public.atl-paas.netinitialsD-6.png"}}, "nickname": "dan77062", "type": "user", "account_id": "557058:e0e36946-cb60-4776-8f47-2e9a0285ad35"}, "message": {"raw": null, "markup": "markdown", "html": "", "type": "rendered"}, "type": "issue_change", "id": 31945365}, {"changes": {"content": {"new": "The controller manager crashes as it tries to initialize the hardware interface.  This continues after updating with the fix for the $HOME/valkyrie directory missing issue (issue #4).  See the log below.\r\n\r\nI am wondering if it is a race condition.  It w", "old": "The controller manager crashes as it tries to initialize the hardware interface.  This continues after updating with the fix for the $HOME/valkyrie directory missing issue (issue #4).  See the log below.\r\n\r\nI am wondering if it is a race condition.  It w"}}, "links": {"self": {"href": "data/repositories/osrf/srcsim/issues/6/changes/31968194.json"}, "html": {"href": "#!/osrf/srcsim/issues/6#comment-31968194"}}, "issue": {"links": {"self": {"href": "data/repositories/osrf/srcsim/issues/6.json"}}, "type": "issue", "id": 6, "repository": {"links": {"self": {"href": "data/repositories/osrf/srcsim.json"}, "html": {"href": "#!/osrf/srcsim"}, "avatar": {"href": "data/bytebucket.org/ravatar/{c41021d9-0217-4628-999d-7f8d82f98dcb}ts=c_plus_plus"}}, "type": "repository", "name": "srcsim", "full_name": "osrf/srcsim", "uuid": "{c41021d9-0217-4628-999d-7f8d82f98dcb}"}, "title": "controller manager dies"}, "created_on": "2016-11-07T18:08:53.734631+00:00", "user": {"display_name": "Steve Peters", "uuid": "{2ccfed09-18b8-4921-8d58-15ef01092802}", "links": {"self": {"href": "https://api.bitbucket.org/2.0/users/%7B2ccfed09-18b8-4921-8d58-15ef01092802%7D"}, "html": {"href": "https://bitbucket.org/%7B2ccfed09-18b8-4921-8d58-15ef01092802%7D/"}, "avatar": {"href": "data/secure.gravatar.com/avatar/1fb4816dad9e68337d3096f750951f6cd=httpsavatar-management--avatars.us-west-2.prod.public.atl-paas.netinitialsSP-1.png"}}, "nickname": "Steven Peters", "type": "user", "account_id": "557058:5de38267-b118-494c-aa76-4fab35448816"}, "message": {"raw": null, "markup": "markdown", "html": "", "type": "rendered"}, "type": "issue_change", "id": 31968194}, {"changes": {"attachment": {"new": "roslaunch-Mingo-Mtn-Robotics-24096.log", "old": null}}, "links": {"self": {"href": "data/repositories/osrf/srcsim/issues/6/changes/31997586.json"}, "html": {"href": "#!/osrf/srcsim/issues/6#comment-31997586"}}, "issue": {"links": {"self": {"href": "data/repositories/osrf/srcsim/issues/6.json"}}, "type": "issue", "id": 6, "repository": {"links": {"self": {"href": "data/repositories/osrf/srcsim.json"}, "html": {"href": "#!/osrf/srcsim"}, "avatar": {"href": "data/bytebucket.org/ravatar/{c41021d9-0217-4628-999d-7f8d82f98dcb}ts=c_plus_plus"}}, "type": "repository", "name": "srcsim", "full_name": "osrf/srcsim", "uuid": "{c41021d9-0217-4628-999d-7f8d82f98dcb}"}, "title": "controller manager dies"}, "created_on": "2016-11-08T16:51:37.830876+00:00", "user": {"display_name": "sringer99", "uuid": "{7ef70da9-f328-4ba4-b181-862c6f2a45bd}", "links": {"self": {"href": "https://api.bitbucket.org/2.0/users/%7B7ef70da9-f328-4ba4-b181-862c6f2a45bd%7D"}, "html": {"href": "https://bitbucket.org/%7B7ef70da9-f328-4ba4-b181-862c6f2a45bd%7D/"}, "avatar": {"href": "data/secure.gravatar.com/avatar/5494aa6c922a68310e0342fedad15f8dd=httpsavatar-management--avatars.us-west-2.prod.public.atl-paas.netinitialsS-1.png"}}, "nickname": "sringer99", "type": "user", "account_id": "557058:f8291867-5c5f-4d10-868d-ea8e2c04eca6"}, "message": {"raw": "Here are the log files for my last fail", "markup": "markdown", "html": "<p>Here are the log files for my last fail</p>", "type": "rendered"}, "type": "issue_change", "id": 31997586}, {"changes": {"assignee_account_id": {"new": "557058:5de38267-b118-494c-aa76-4fab35448816", "old": ""}, "assignee": {"new": "scpeters", "old": ""}}, "links": {"self": {"href": "data/repositories/osrf/srcsim/issues/6/changes/32159016.json"}, "html": {"href": "#!/osrf/srcsim/issues/6#comment-32159016"}}, "issue": {"links": {"self": {"href": "data/repositories/osrf/srcsim/issues/6.json"}}, "type": "issue", "id": 6, "repository": {"links": {"self": {"href": "data/repositories/osrf/srcsim.json"}, "html": {"href": "#!/osrf/srcsim"}, "avatar": {"href": "data/bytebucket.org/ravatar/{c41021d9-0217-4628-999d-7f8d82f98dcb}ts=c_plus_plus"}}, "type": "repository", "name": "srcsim", "full_name": "osrf/srcsim", "uuid": "{c41021d9-0217-4628-999d-7f8d82f98dcb}"}, "title": "controller manager dies"}, "created_on": "2016-11-14T22:43:36.480549+00:00", "user": {"display_name": "Nate Koenig", "uuid": "{c862cdd9-fcc8-4419-9fc7-e20db14b8fcb}", "links": {"self": {"href": "https://api.bitbucket.org/2.0/users/%7Bc862cdd9-fcc8-4419-9fc7-e20db14b8fcb%7D"}, "html": {"href": "https://bitbucket.org/%7Bc862cdd9-fcc8-4419-9fc7-e20db14b8fcb%7D/"}, "avatar": {"href": "https://avatar-management--avatars.us-west-2.prod.public.atl-paas.net/557058:095b1e12-74ed-4e20-b44f-2f0745b616e0/ca24bb11-4787-4b14-a20d-d91835e9bde2/128"}}, "nickname": "Nathan Koenig", "type": "user", "account_id": "557058:095b1e12-74ed-4e20-b44f-2f0745b616e0"}, "message": {"raw": null, "markup": "markdown", "html": "", "type": "rendered"}, "type": "issue_change", "id": 32159016}, {"changes": {"state": {"new": "resolved", "old": "new"}}, "links": {"self": {"href": "data/repositories/osrf/srcsim/issues/6/changes/32605837.json"}, "html": {"href": "#!/osrf/srcsim/issues/6#comment-32605837"}}, "issue": {"links": {"self": {"href": "data/repositories/osrf/srcsim/issues/6.json"}}, "type": "issue", "id": 6, "repository": {"links": {"self": {"href": "data/repositories/osrf/srcsim.json"}, "html": {"href": "#!/osrf/srcsim"}, "avatar": {"href": "data/bytebucket.org/ravatar/{c41021d9-0217-4628-999d-7f8d82f98dcb}ts=c_plus_plus"}}, "type": "repository", "name": "srcsim", "full_name": "osrf/srcsim", "uuid": "{c41021d9-0217-4628-999d-7f8d82f98dcb}"}, "title": "controller manager dies"}, "created_on": "2016-12-02T00:15:01.691124+00:00", "user": {"display_name": "dan", "uuid": "{a93bd0ec-35fc-49a5-aa8a-b0b57403c2d0}", "links": {"self": {"href": "https://api.bitbucket.org/2.0/users/%7Ba93bd0ec-35fc-49a5-aa8a-b0b57403c2d0%7D"}, "html": {"href": "https://bitbucket.org/%7Ba93bd0ec-35fc-49a5-aa8a-b0b57403c2d0%7D/"}, "avatar": {"href": "data/secure.gravatar.com/avatar/dd56d3105d7602d83d5c35a320f6b36cd=httpsavatar-management--avatars.us-west-2.prod.public.atl-paas.netinitialsD-6.png"}}, "nickname": "dan77062", "type": "user", "account_id": "557058:e0e36946-cb60-4776-8f47-2e9a0285ad35"}, "message": {"raw": "The two core problem is solved-- thanks!", "markup": "markdown", "html": "<p>The two core problem is solved-- thanks!</p>", "type": "rendered"}, "type": "issue_change", "id": 32605837}], "page": 1, "size": 6}